functionsclient/__init__.py
functionsclient/client.py
functionsclient/tests/__init__.py
functionsclient/tests/base.py
functionsclient/tests/test_scenarios.py
functionsclient/v1/__init__.py
functionsclient/v1/apps.py
functionsclient/v1/client.py
functionsclient/v1/routes.py
functionsclient/v1/tasks.py
python_functionsclient-0.0.3.dist-info/DESCRIPTION.rst
python_functionsclient-0.0.3.dist-info/METADATA
python_functionsclient-0.0.3.dist-info/RECORD
python_functionsclient-0.0.3.dist-info/WHEEL
python_functionsclient-0.0.3.dist-info/metadata.json
python_functionsclient-0.0.3.dist-info/top_level.txt
python_functionsclient-0.0.3.dist-info/zip-safe
