Metadata-Version: 2.0
Name: python-functionsclient
Version: 0.0.3
Summary: Functions v1 Python API
Home-page: https://open.iron.io/
Author: Denis Makogon
Author-email: denis@iron.io
License: License :: OSI Approved :: Apache Software License
Keywords: functions,async,Python API
Platform: Linux
Platform: Mac OS-X
Platform: Unix
Classifier: License :: OSI Approved :: Apache Software License
Classifier: Intended Audience :: Information Technology
Classifier: Intended Audience :: System Administrators
Classifier: Intended Audience :: Developers
Classifier: Programming Language :: Python :: 3.5
Classifier: Topic :: Software Development :: Libraries :: Python Modules
Classifier: Topic :: System :: Distributed Computing
Classifier: Operating System :: Microsoft :: Windows
Classifier: Operating System :: POSIX
Classifier: Operating System :: Unix
Classifier: Operating System :: MacOS
Requires-Dist: aiohttp (>=1.1.6)
